django_dashboards_app/__init__.py
django_dashboards_app/admin.py
django_dashboards_app/apps.py
django_dashboards_app/filters.py
django_dashboards_app/forms.py
django_dashboards_app/generators.py
django_dashboards_app/models.py
django_dashboards_app/settings.py
django_dashboards_app/tests.py
django_dashboards_app/urls.py
django_dashboards_app/views.py
django_dashboards_app/management/__init__.py
django_dashboards_app/management/commands/__init__.py
django_dashboards_app/management/commands/generate.py
django_dashboards_app/migrations/__init__.py
django_dashboards_app/templatetags/__init__.py
django_dashboards_app/templatetags/dashboard_tags.py
django_dashboards_app-1.0.3.dist-info/LICENSE.txt
django_dashboards_app-1.0.3.dist-info/METADATA
django_dashboards_app-1.0.3.dist-info/WHEEL
django_dashboards_app-1.0.3.dist-info/top_level.txt
django_dashboards_app-1.0.3.dist-info/RECORD
