Metadata-Version: 2.1
Name: django-dashboards-app
Version: 1.0.3
Summary: Django Admin for Developers and Django Dahsboards for Clients
Home-page: https://gitlab.com/albertosanmartinmartinez/django-dashboards
Author: Alberto Sanmartin Martinez
Author-email: info@albertosanmartinmartinez.es
Maintainer: Alberto Sanmartin Martinez
Maintainer-email: info@albertosanmartinmartinez.es
License: GPLv3
Platform: UNKNOWN
Classifier: Programming Language :: Python :: 3
Classifier: License :: OSI Approved :: GNU General Public License v3 (GPLv3)
Classifier: Operating System :: OS Independent
Classifier: Framework :: Django
Classifier: Natural Language :: English
Classifier: Development Status :: 4 - Beta
Classifier: Intended Audience :: Information Technology
Classifier: Topic :: Software Development :: Libraries :: Application Frameworks
Requires-Python: >=3
Requires-Dist: Django (>=3)
